everything_search/__init__.py
everything_search/gui_main.py
everything_search/cli/__init__.py
everything_search/cli/index_cli.py
everything_search/cli/search_cli.py
everything_search/core/__init__.py
everything_search/core/config_manager.py
everything_search/core/database.py
everything_search/core/file_indexer.py
everything_search/core/file_watcher.py
everything_search/core/search_engine.py
everything_search/gui/__init__.py
everything_search/gui/dialogs.py
everything_search/gui/main_window.py
everything_search/gui/search_tab.py
everything_search/gui/settings_tab.py
everything_search/gui/worker_threads.py
everything_search-1.0.1.dist-info/METADATA
everything_search-1.0.1.dist-info/WHEEL
everything_search-1.0.1.dist-info/entry_points.txt
everything_search-1.0.1.dist-info/RECORD
