Metadata-Version: 2.4
Name: everything-search
Version: 1.0.1
Summary: 高性能文件搜索工具 - 类似于Windows Everything的macOS解决方案
Project-URL: Homepage, https://github.com/duolabmeng6/everything-for-mac
Project-URL: Repository, https://github.com/duolabmeng6/everything-for-mac
Project-URL: Documentation, https://github.com/duolabmeng6/everything-for-mac#readme
Project-URL: Bug Tracker, https://github.com/duolabmeng6/everything-for-mac/issues
Author-email: duolabmeng6 <1715109585@gmail.com>
License: MIT
Keywords: desktop,everything,file-search,gui,indexing,macos,search-engine
Classifier: Development Status :: 4 - Beta
Classifier: Intended Audience :: Developers
Classifier: Intended Audience :: End Users/Desktop
Classifier: License :: OSI Approved :: MIT License
Classifier: Operating System :: MacOS
Classifier: Programming Language :: Python :: 3
Classifier: Programming Language :: Python :: 3.9
Classifier: Programming Language :: Python :: 3.10
Classifier: Programming Language :: Python :: 3.11
Classifier: Programming Language :: Python :: 3.12
Classifier: Programming Language :: Python :: 3.13
Classifier: Topic :: Desktop Environment :: File Managers
Classifier: Topic :: System :: Filesystems
Classifier: Topic :: Utilities
Requires-Python: >=3.9
Requires-Dist: pyside6>=6.5.0
Requires-Dist: watchdog>=6.0.0
Provides-Extra: dev
